{
  "main": {
    "id": "7dbc5b196a11256c",
    "type": "split",
    "children": [
      {
        "id": "44459413d56572a6",
        "type": "tabs",
        "children": [
          {
            "id": "e53f15967b553233",
            "type": "leaf",
            "state": {
              "type": "markdown",
              "state": {
                "file": "diary/黑苹果dmg创建.md",
                "mode": "source",
                "source": false
              }
            }
          }
        ]
      }
    ],
    "direction": "vertical"
  },
  "left": {
    "id": "7cc9ed9b036b42af",
    "type": "split",
    "children": [
      {
        "id": "bab27bfa5e0c45d6",
        "type": "tabs",
        "children": [
          {
            "id": "2fe2f08c50ea59c7",
            "type": "leaf",
            "state": {
              "type": "file-explorer",
              "state": {
                "sortOrder": "alphabetical"
              }
            }
          },
          {
            "id": "484f6c2b238326e6",
            "type": "leaf",
            "state": {
              "type": "search",
              "state": {
                "query": "tag:GitHub",
                "matchingCase": false,
                "explainSearch": false,
                "collapseAll": false,
                "extraContext": false,
                "sortOrder": "alphabetical"
              }
            }
          },
          {
            "id": "a43af7e3cc37512d",
            "type": "leaf",
            "state": {
              "type": "bookmarks",
              "state": {}
            }
          },
          {
            "id": "6030f1aaf3554a92",
            "type": "leaf",
            "state": {
              "type": "mk-path-view",
              "state": {}
            }
          }
        ]
      }
    ],
    "direction": "horizontal",
    "width": 288.5
  },
  "right": {
    "id": "45dfc9613c5bf423",
    "type": "split",
    "children": [
      {
        "id": "0f1a1ff5f6df6ddf",
        "type": "tabs",
        "children": [
          {
            "id": "d368fc127de9c6ca",
            "type": "leaf",
            "state": {
              "type": "backlink",
              "state": {
                "file": "diary/黑苹果dmg创建.md",
                "collapseAll": false,
                "extraContext": false,
                "sortOrder": "alphabetical",
                "showSearch": false,
                "searchQuery": "",
                "backlinkCollapsed": false,
                "unlinkedCollapsed": true
              }
            }
          },
          {
            "id": "1e06a17904d20217",
            "type": "leaf",
            "state": {
              "type": "outgoing-link",
              "state": {
                "file": "diary/黑苹果dmg创建.md",
                "linksCollapsed": false,
                "unlinkedCollapsed": true
              }
            }
          },
          {
            "id": "92462f91136a9a13",
            "type": "leaf",
            "state": {
              "type": "tag",
              "state": {
                "sortOrder": "frequency",
                "useHierarchy": true
              }
            }
          },
          {
            "id": "0060822709c6163b",
            "type": "leaf",
            "state": {
              "type": "outline",
              "state": {
                "file": "diary/黑苹果dmg创建.md"
              }
            }
          },
          {
            "id": "5d10dfce403b3152",
            "type": "leaf",
            "state": {
              "type": "calendar",
              "state": {}
            }
          },
          {
            "id": "c6cbe160898b717e",
            "type": "leaf",
            "state": {
              "type": "make-context-view",
              "state": {}
            }
          }
        ],
        "currentTab": 5
      }
    ],
    "direction": "horizontal",
    "width": 300
  },
  "left-ribbon": {
    "hiddenItems": {
      "switcher:打开快速切换": false,
      "graph:查看关系图谱": false,
      "daily-notes:打开/创建今天的日记": false,
      "templates:插入模板": false,
      "command-palette:打开命令面板": false,
      "cmdr:Shell commands: Execute: git push": false,
      "cmdr:Shell commands: Execute: git pull": false
    }
  },
  "active": "e53f15967b553233",
  "lastOpenFiles": [
    "Vault.md",
    "GitHub action/简介.md",
    "diary/黑苹果dmg创建.md",
    "Tags",
    "diary/海阔世界规则编写.md",
    "diary/阅读设置.md",
    "diary/vidhub食用步骤.md",
    "diary/注册美区AppleID.md",
    "diary/Node.js—切图.md",
    "diary/幽默.md",
    "diary/Mac 下的定时任务工具：Launchctl.md",
    "diary/QQ辅助插件.md",
    "diary/2024-05-10.md",
    "Excalidraw/Drawing 2024-07-08 08.43.20.excalidraw.md",
    "Excalidraw/Drawing 2024-07-08 08.47.49.excalidraw.md",
    "考公/判断推理/1、图形推理.md",
    "考公/判断推理/2、类比推理.md",
    "考公/判断推理/3、定义判断.md",
    "考公/判断推理/4、逻辑推理.md",
    "diary/2024-06-18.md",
    "git/git安装.md",
    "template/日记.md",
    "template/atom.md",
    "考公/资料分析/3、速算技巧.md",
    "考公/资料分析/2、结构阅读法.md",
    "考公/资料分析/1、统计术语.md",
    "考公/资料分析",
    "考公/判断推理",
    "考公",
    "template",
    "node.js/node.js.md",
    "node.js",
    "html",
    "git",
    "exam/解剖学",
    "exam",
    "Excalidraw/Pasted Image 20240504001522_540.png",
    "Resource/Src/328.jpg",
    "未命名.canvas",
    "未命名 1.canvas"
  ]
}